LICENSE
README.md
setup.py
bio_pypage.egg-info/PKG-INFO
bio_pypage.egg-info/SOURCES.txt
bio_pypage.egg-info/dependency_links.txt
bio_pypage.egg-info/requires.txt
bio_pypage.egg-info/top_level.txt
pypage/__init__.py
pypage/heatmap.py
pypage/hist.py
pypage/information.py
pypage/page.py
pypage/utils.py
pypage/io/__init__.py
pypage/io/accession_types.py
pypage/io/expression.py
pypage/io/ontology.py
tests/test_enrichment.py
tests/test_expression.py
tests/test_heatmap.py
tests/test_info.py
tests/test_ontology.py
tests/test_run.py
tests/test_run_2.py
tests/test_run_with_simulated_data.py