Metadata-Version: 2.1
Name: bio-pypage
Version: 0.1.7
Summary: Python implementation of the PAGE algorithm
Home-page: https://github.com/goodarzilab/pypage
Author: Artemy Bakulin, Noam Teyssier
Author-email: logic2000.bakulin@gmail.com
License: UNKNOWN
Platform: UNKNOWN
Classifier: Programming Language :: Python :: 3
Classifier: License :: OSI Approved :: MIT License
Classifier: Operating System :: OS Independent
License-File: LICENSE
